[
{
	"key":"H12_100A",
	"organism":"Sf",
	"specification":"Strain(s): 5348",
	"source":"Zaika_94",
	"details":"SfB01",
	"b_f":"Culture_medium",
	"meas_method":"plate_count",
	"condition":"NaCl(%):0.5, Nitrite(ppm):100, anaerobic",
	"temp":"28",
	"pH":"6.5",
	"aw":"0.997",
	"property":"",
	"tObs":"53",
	"logc":"0;2.19;3;2.22;5;3.11;9;4.17;25;7.69;29;8.13;49;8.43;53;8.43",
	"logcVar":"6.24",
	"spec_rate":"0.5524",
	"assumed":"aw",
	"comment":"",
	"in_on":"In: BHIB"
},
{
	"key":"H12_100B",
	"organism":"Sf",
	"specification":"Strain(s): 5348",
	"source":"Zaika_94",
	"details":"SfB01",
	"b_f":"Culture_medium",
	"meas_method":"plate_count",
	"condition":"NaCl(%):0.5, Nitrite(ppm):100, anaerobic",
	"temp":"28",
	"pH":"6.5",
	"aw":"0.997",
	"property":"",
	"tObs":"53",
	"logc":"0;2.11;3;2.34;5;3.03;9;4.3;25;7.87;29;8.27;49;8.38;53;8.41",
	"logcVar":"6.3",
	"spec_rate":"0.5885",
	"assumed":"aw",
	"comment":"",
	"in_on":"In: BHIB"
},
{
	"key":"H12_200A",
	"organism":"Sf",
	"specification":"Strain(s): 5348",
	"source":"Zaika_94",
	"details":"SfB01",
	"b_f":"Culture_medium",
	"meas_method":"plate_count",
	"condition":"NaCl(%):0.5, Nitrite(ppm):200, anaerobic",
	"temp":"28",
	"pH":"6.5",
	"aw":"0.997",
	"property":"",
	"tObs":"123",
	"logc":"0;2.13;3;2.22;5;2.65;9;3.72;25;6.77;29;7.69;49;8.13;53;7.92;123;8.46",
	"logcVar":"6.33",
	"spec_rate":"0.4741",
	"assumed":"aw",
	"comment":"",
	"in_on":"In: BHIB"
},
{
	"key":"H12_200B",
	"organism":"Sf",
	"specification":"Strain(s): 5348",
	"source":"Zaika_94",
	"details":"SfB01",
	"b_f":"Culture_medium",
	"meas_method":"plate_count",
	"condition":"NaCl(%):0.5, Nitrite(ppm):200, anaerobic",
	"temp":"28",
	"pH":"6.5",
	"aw":"0.997",
	"property":"",
	"tObs":"123",
	"logc":"0;2.11;3;2.22;5;2.61;9;3.16;25;5.09;29;5.43;49;8.18;53;8.1;123;8.29",
	"logcVar":"6.18",
	"spec_rate":"0.2959",
	"assumed":"aw",
	"comment":"",
	"in_on":"In: BHIB"
},
{
	"key":"H13_0A",
	"organism":"Sf",
	"specification":"Strain(s): 5348",
	"source":"Zaika_94",
	"details":"SfB01",
	"b_f":"Culture_medium",
	"meas_method":"plate_count",
	"condition":"NaCl(%):2.5, anaerobic",
	"temp":"28",
	"pH":"6.5",
	"aw":"0.986",
	"property":"",
	"tObs":"51",
	"logc":"0;2.53;4;3.14;6;3.9;22;8.4;27;8.34;47;7.92;51;8.19",
	"logcVar":"5.87",
	"spec_rate":"0.6988",
	"assumed":"aw",
	"comment":"",
	"in_on":"In: BHIB"
},
{
	"key":"H13_0B",
	"organism":"Sf",
	"specification":"Strain(s): 5348",
	"source":"Zaika_94",
	"details":"SfB01",
	"b_f":"Culture_medium",
	"meas_method":"plate_count",
	"condition":"NaCl(%):2.5, anaerobic",
	"temp":"28",
	"pH":"6.5",
	"aw":"0.986",
	"property":"",
	"tObs":"51",
	"logc":"0;2.53;4;3.27;6;3.91;22;8.42;27;8.3;47;8.19;51;8.16",
	"logcVar":"5.89",
	"spec_rate":"1.04",
	"assumed":"aw",
	"comment":"",
	"in_on":"In: BHIB"
},
{
	"key":"H13_100A",
	"organism":"Sf",
	"specification":"Strain(s): 5348",
	"source":"Zaika_94",
	"details":"SfB01",
	"b_f":"Culture_medium",
	"meas_method":"plate_count",
	"condition":"NaCl(%):2.5, Nitrite(ppm):100, anaerobic",
	"temp":"28",
	"pH":"6.5",
	"aw":"0.986",
	"property":"",
	"tObs":"51",
	"logc":"0;2.8;4;3.2;6;3.88;22;7.72;27;7.65;47;8.08;51;8.08",
	"logcVar":"5.28",
	"spec_rate":"0.5533",
	"assumed":"aw",
	"comment":"",
	"in_on":"In: BHIB"
},
{
	"key":"H13_100B",
	"organism":"Sf",
	"specification":"Strain(s): 5348",
	"source":"Zaika_94",
	"details":"SfB01",
	"b_f":"Culture_medium",
	"meas_method":"plate_count",
	"condition":"NaCl(%):2.5, Nitrite(ppm):100, anaerobic",
	"temp":"28",
	"pH":"6.5",
	"aw":"0.986",
	"property":"",
	"tObs":"51",
	"logc":"0;2.8;4;3.28;6;3.85;22;7.81;27;8.4;47;8.48;51;8.48",
	"logcVar":"5.68",
	"spec_rate":"0.6228",
	"assumed":"aw",
	"comment":"",
	"in_on":"In: BHIB"
},
{
	"key":"H13_200A",
	"organism":"Sf",
	"specification":"Strain(s): 5348",
	"source":"Zaika_94",
	"details":"SfB01",
	"b_f":"Culture_medium",
	"meas_method":"plate_count",
	"condition":"NaCl(%):2.5, Nitrite(ppm):200, anaerobic",
	"temp":"28",
	"pH":"6.5",
	"aw":"0.986",
	"property":"",
	"tObs":"51",
	"logc":"0;2.77;4;3.11;6;3.66;22;6.12;27;7.41;47;8.05;51;8.07",
	"logcVar":"5.3",
	"spec_rate":"0.3972",
	"assumed":"aw",
	"comment":"",
	"in_on":"In: BHIB"
},
{
	"key":"H13_200B",
	"organism":"Sf",
	"specification":"Strain(s): 5348",
	"source":"Zaika_94",
	"details":"SfB01",
	"b_f":"Culture_medium",
	"meas_method":"plate_count",
	"condition":"NaCl(%):2.5, Nitrite(ppm):200, anaerobic",
	"temp":"28",
	"pH":"6.5",
	"aw":"0.986",
	"property":"",
	"tObs":"51",
	"logc":"0;2.77;4;3.11;6;3.69;22;7.49;27;8.02;47;7.86;51;8.09",
	"logcVar":"5.32",
	"spec_rate":"0.6109",
	"assumed":"aw",
	"comment":"",
	"in_on":"In: BHIB"
},
{
	"key":"H14_0A",
	"organism":"Sf",
	"specification":"Strain(s): 5348",
	"source":"Zaika_94",
	"details":"SfB01",
	"b_f":"Culture_medium",
	"meas_method":"plate_count",
	"condition":"NaCl(%):4, anaerobic",
	"temp":"28",
	"pH":"6.5",
	"aw":"0.977",
	"property":"",
	"tObs":"54",
	"logc":"0;3.02;5;3.05;23;5.82;31;7.89;51;8.27;54;8.27",
	"logcVar":"5.25",
	"spec_rate":"0.6956",
	"assumed":"aw",
	"comment":"",
	"in_on":"In: BHIB"
},
{
	"key":"H14_0B",
	"organism":"Sf",
	"specification":"Strain(s): 5348",
	"source":"Zaika_94",
	"details":"SfB01",
	"b_f":"Culture_medium",
	"meas_method":"plate_count",
	"condition":"NaCl(%):4, anaerobic",
	"temp":"28",
	"pH":"6.5",
	"aw":"0.977",
	"property":"",
	"tObs":"54",
	"logc":"0;3.02;5;3.39;23;6.47;28;7.66;31;7.33;51;7.47;54;7.41",
	"logcVar":"4.64",
	"spec_rate":"0.3958",
	"assumed":"aw",
	"comment":"",
	"in_on":"In: BHIB"
},
{
	"key":"H14_100A",
	"organism":"Sf",
	"specification":"Strain(s): 5348",
	"source":"Zaika_94",
	"details":"SfB01",
	"b_f":"Culture_medium",
	"meas_method":"plate_count",
	"condition":"NaCl(%):4, Nitrite(ppm):100, anaerobic",
	"temp":"28",
	"pH":"6.5",
	"aw":"0.977",
	"property":"",
	"tObs":"54",
	"logc":"0;2.97;5;3.01;23;5.44;28;7.46;31;7.33;51;7.43;54;7.43",
	"logcVar":"4.49",
	"spec_rate":"0.3525",
	"assumed":"aw",
	"comment":"",
	"in_on":"In: BHIB"
},
{
	"key":"H14_100B",
	"organism":"Sf",
	"specification":"Strain(s): 5348",
	"source":"Zaika_94",
	"details":"SfB01",
	"b_f":"Culture_medium",
	"meas_method":"plate_count",
	"condition":"NaCl(%):4, Nitrite(ppm):100, anaerobic",
	"temp":"28",
	"pH":"6.5",
	"aw":"0.977",
	"property":"",
	"tObs":"54",
	"logc":"0;2.97;5;2.99;23;5.14;28;7.49;31;7.58;51;7.76;54;7.76",
	"logcVar":"4.79",
	"spec_rate":"0.3592",
	"assumed":"aw",
	"comment":"",
	"in_on":"In: BHIB"
},
{
	"key":"H15_0A",
	"organism":"Sf",
	"specification":"Strain(s): 5348",
	"source":"Zaika_94",
	"details":"SfB01",
	"b_f":"Culture_medium",
	"meas_method":"plate_count",
	"condition":"NaCl(%):0.5, anaerobic",
	"temp":"28",
	"pH":"7.5",
	"aw":"0.997",
	"property":"",
	"tObs":"51",
	"logc":"0;2.85;3;3.33;5;4.31;8;5.15;24;8.7;29.5;8.64;51;8.61",
	"logcVar":"5.85",
	"spec_rate":"0.7009",
	"assumed":"aw",
	"comment":"",
	"in_on":"In: BHIB"
},
{
	"key":"H15_0B",
	"organism":"Sf",
	"specification":"Strain(s): 5348",
	"source":"Zaika_94",
	"details":"SfB01",
	"b_f":"Culture_medium",
	"meas_method":"plate_count",
	"condition":"NaCl(%):0.5, anaerobic",
	"temp":"28",
	"pH":"7.5",
	"aw":"0.997",
	"property":"",
	"tObs":"51",
	"logc":"0;2.84;3;3.42;5;4.3;8;5.11;24;8.67;29.5;8.71;51;8.65",
	"logcVar":"5.87",
	"spec_rate":"0.6829",
	"assumed":"aw",
	"comment":"",
	"in_on":"In: BHIB"
},
{
	"key":"H15_0C",
	"organism":"Sf",
	"specification":"Strain(s): 5348",
	"source":"Zaika_94",
	"details":"SfB01",
	"b_f":"Culture_medium",
	"meas_method":"plate_count",
	"condition":"NaCl(%):0.5, anaerobic",
	"temp":"28",
	"pH":"7.5",
	"aw":"0.997",
	"property":"",
	"tObs":"51",
	"logc":"0;2.83;3;3.44;5;4.27;8;5.11;24;8.75;29.5;8.91;51;8.79",
	"logcVar":"6.08",
	"spec_rate":"0.6781",
	"assumed":"aw",
	"comment":"",
	"in_on":"In: BHIB"
},
{
	"key":"H15_200A",
	"organism":"Sf",
	"specification":"Strain(s): 5348",
	"source":"Zaika_94",
	"details":"SfB01",
	"b_f":"Culture_medium",
	"meas_method":"plate_count",
	"condition":"NaCl(%):0.5, Nitrite(ppm):200, anaerobic",
	"temp":"28",
	"pH":"7.5",
	"aw":"0.997",
	"property":"",
	"tObs":"51",
	"logc":"0;2.87;3;3.37;5;4.27;8;5.1;24;8.66;29.5;8.66;51;8.64",
	"logcVar":"5.79",
	"spec_rate":"0.6765",
	"assumed":"aw",
	"comment":"",
	"in_on":"In: BHIB"
},
{
	"key":"H15_200B",
	"organism":"Sf",
	"specification":"Strain(s): 5348",
	"source":"Zaika_94",
	"details":"SfB01",
	"b_f":"Culture_medium",
	"meas_method":"plate_count",
	"condition":"NaCl(%):0.5, Nitrite(ppm):200, anaerobic",
	"temp":"28",
	"pH":"7.5",
	"aw":"0.997",
	"property":"",
	"tObs":"51",
	"logc":"0;2.98;3;3.39;5;4.24;8;5.15;24;8.67;29.5;8.63;51;8.61",
	"logcVar":"5.69",
	"spec_rate":"0.6634",
	"assumed":"aw",
	"comment":"",
	"in_on":"In: BHIB"
},
{
	"key":"H15_200C",
	"organism":"Sf",
	"specification":"Strain(s): 5348",
	"source":"Zaika_94",
	"details":"SfB01",
	"b_f":"Culture_medium",
	"meas_method":"plate_count",
	"condition":"NaCl(%):0.5, Nitrite(ppm):200, anaerobic",
	"temp":"28",
	"pH":"7.5",
	"aw":"0.997",
	"property":"",
	"tObs":"51",
	"logc":"0;2.84;3;3.33;5;4.24;8;5.07;24;8.82;29.5;8.72;51;8.71",
	"logcVar":"5.98",
	"spec_rate":"0.6903",
	"assumed":"aw",
	"comment":"",
	"in_on":"In: BHIB"
},
{
	"key":"H16_0A",
	"organism":"Sf",
	"specification":"Strain(s): 5348",
	"source":"Zaika_94",
	"details":"SfB01",
	"b_f":"Culture_medium",
	"meas_method":"plate_count",
	"condition":"NaCl(%):2.5, anaerobic",
	"temp":"28",
	"pH":"7.5",
	"aw":"0.986",
	"property":"",
	"tObs":"49",
	"logc":"0;2.94;3;3.03;5;3.39;7;4.08;11;5;24;8.6;28;8.81;33;8.54;49;8.67",
	"logcVar":"5.87",
	"spec_rate":"0.7654",
	"assumed":"aw",
	"comment":"",
	"in_on":"In: BHIB"
},
{
	"key":"H16_0B",
	"organism":"Sf",
	"specification":"Strain(s): 5348",
	"source":"Zaika_94",
	"details":"SfB01",
	"b_f":"Culture_medium",
	"meas_method":"plate_count",
	"condition":"NaCl(%):2.5, anaerobic",
	"temp":"28",
	"pH":"7.5",
	"aw":"0.986",
	"property":"",
	"tObs":"49",
	"logc":"0;2.9;3;2.88;5;3.29;7;4.04;11;4.69;24;8.7;28;8.63;33;8.78;49;8.92",
	"logcVar":"6.04",
	"spec_rate":"0.7771",
	"assumed":"aw",
	"comment":"",
	"in_on":"In: BHIB"
},
{
	"key":"H16_0C",
	"organism":"Sf",
	"specification":"Strain(s): 5348",
	"source":"Zaika_94",
	"details":"SfB01",
	"b_f":"Culture_medium",
	"meas_method":"plate_count",
	"condition":"NaCl(%):2.5, anaerobic",
	"temp":"28",
	"pH":"7.5",
	"aw":"0.986",
	"property":"",
	"tObs":"49",
	"logc":"0;2.97;3;3.01;5;3.36;7;4.13;11;4.56;24;8.4;28;8.48;33;8.45;49;8.65",
	"logcVar":"5.68",
	"spec_rate":"0.7258",
	"assumed":"aw",
	"comment":"",
	"in_on":"In: BHIB"
},
{
	"key":"H16_200A",
	"organism":"Sf",
	"specification":"Strain(s): 5348",
	"source":"Zaika_94",
	"details":"SfB01",
	"b_f":"Culture_medium",
	"meas_method":"plate_count",
	"condition":"NaCl(%):2.5, Nitrite(ppm):200, anaerobic",
	"temp":"28",
	"pH":"7.5",
	"aw":"0.986",
	"property":"",
	"tObs":"49",
	"logc":"0;2.86;3;2.96;5;3.29;7;3.87;11;5;24;8.03;28;8.47;33;8.29;49;8.51",
	"logcVar":"5.65",
	"spec_rate":"0.6424",
	"assumed":"aw",
	"comment":"",
	"in_on":"In: BHIB"
},
{
	"key":"H16_200B",
	"organism":"Sf",
	"specification":"Strain(s): 5348",
	"source":"Zaika_94",
	"details":"SfB01",
	"b_f":"Culture_medium",
	"meas_method":"plate_count",
	"condition":"NaCl(%):2.5, Nitrite(ppm):200, anaerobic",
	"temp":"28",
	"pH":"7.5",
	"aw":"0.986",
	"property":"",
	"tObs":"49",
	"logc":"0;2.92;3;2.88;5;3.25;7;3.93;11;4.97;24;8.1;28;8.54;33;8.47;49;8.83",
	"logcVar":"5.95",
	"spec_rate":"0.6275",
	"assumed":"aw",
	"comment":"",
	"in_on":"In: BHIB"
},
{
	"key":"H16_200C",
	"organism":"Sf",
	"specification":"Strain(s): 5348",
	"source":"Zaika_94",
	"details":"SfB01",
	"b_f":"Culture_medium",
	"meas_method":"plate_count",
	"condition":"NaCl(%):2.5, Nitrite(ppm):200, anaerobic",
	"temp":"28",
	"pH":"7.5",
	"aw":"0.986",
	"property":"",
	"tObs":"49",
	"logc":"0;2.86;3;2.8;5;3.17;7;3.92;11;4.89;24;8.1;28;8.41;33;8.41;49;8.55",
	"logcVar":"5.75",
	"spec_rate":"0.6528",
	"assumed":"aw",
	"comment":"",
	"in_on":"In: BHIB"
},
{
	"key":"H17_0A",
	"organism":"Sf",
	"specification":"Strain(s): 5348",
	"source":"Zaika_94",
	"details":"SfB01",
	"b_f":"Culture_medium",
	"meas_method":"plate_count",
	"condition":"NaCl(%):4, anaerobic",
	"temp":"28",
	"pH":"7.5",
	"aw":"0.977",
	"property":"",
	"tObs":"79",
	"logc":"0;3.08;6.5;2.99;22.5;5.88;27.5;6.24;47.5;6.78;51.5;7.06;73;7.06;79;6.29",
	"logcVar":"4.07",
	"spec_rate":"0.3104",
	"assumed":"aw",
	"comment":"",
	"in_on":"In: BHIB"
},
{
	"key":"H17_0B",
	"organism":"Sf",
	"specification":"Strain(s): 5348",
	"source":"Zaika_94",
	"details":"SfB01",
	"b_f":"Culture_medium",
	"meas_method":"plate_count",
	"condition":"NaCl(%):4, anaerobic",
	"temp":"28",
	"pH":"7.5",
	"aw":"0.977",
	"property":"",
	"tObs":"79",
	"logc":"0;3.03;6.5;3.02;22.5;5.88;27.5;5.39;47.5;8.16;51.5;8.4;73;9.47;79;9.47",
	"logcVar":"6.45",
	"spec_rate":"0.2616",
	"assumed":"aw",
	"comment":"",
	"in_on":"In: BHIB"
},
{
	"key":"H17_0C",
	"organism":"Sf",
	"specification":"Strain(s): 5348",
	"source":"Zaika_94",
	"details":"SfB01",
	"b_f":"Culture_medium",
	"meas_method":"plate_count",
	"condition":"NaCl(%):4, anaerobic",
	"temp":"28",
	"pH":"7.5",
	"aw":"0.977",
	"property":"",
	"tObs":"79",
	"logc":"0;3.03;6.5;3.05;22.5;6;27.5;5.86;47.5;8.2;51.5;8.34;73;9.32;79;9.32",
	"logcVar":"6.29",
	"spec_rate":"0.2655",
	"assumed":"aw",
	"comment":"",
	"in_on":"In: BHIB"
},
{
	"key":"H17_100A",
	"organism":"Sf",
	"specification":"Strain(s): 5348",
	"source":"Zaika_94",
	"details":"SfB01",
	"b_f":"Culture_medium",
	"meas_method":"plate_count",
	"condition":"NaCl(%):4, Nitrite(ppm):100, anaerobic",
	"temp":"28",
	"pH":"7.5",
	"aw":"0.977",
	"property":"",
	"tObs":"73",
	"logc":"0;3.06;6.5;2.92;22.5;5.69;27.5;5.41;47.5;7.67;51.5;7.97;73;7.97",
	"logcVar":"5.05",
	"spec_rate":"0.256",
	"assumed":"aw",
	"comment":"",
	"in_on":"In: BHIB"
},
{
	"key":"H17_100B",
	"organism":"Sf",
	"specification":"Strain(s): 5348",
	"source":"Zaika_94",
	"details":"SfB01",
	"b_f":"Culture_medium",
	"meas_method":"plate_count",
	"condition":"NaCl(%):4, Nitrite(ppm):100, anaerobic",
	"temp":"28",
	"pH":"7.5",
	"aw":"0.977",
	"property":"",
	"tObs":"73",
	"logc":"0;3.03;6.5;3.15;22.5;5.67;27.5;6.22;47.5;7.54;51.5;7.97;73;7.97",
	"logcVar":"4.94",
	"spec_rate":"0.2867",
	"assumed":"aw",
	"comment":"",
	"in_on":"In: BHIB"
},
{
	"key":"H17_100C",
	"organism":"Sf",
	"specification":"Strain(s): 5348",
	"source":"Zaika_94",
	"details":"SfB01",
	"b_f":"Culture_medium",
	"meas_method":"plate_count",
	"condition":"NaCl(%):4, Nitrite(ppm):100, anaerobic",
	"temp":"28",
	"pH":"7.5",
	"aw":"0.977",
	"property":"",
	"tObs":"79",
	"logc":"0;3.03;6.5;2.95;22.5;6;27.5;5.91;47.5;8.79;51.5;8.16;73;8.09;79;8.53",
	"logcVar":"5.84",
	"spec_rate":"0.3095",
	"assumed":"aw",
	"comment":"",
	"in_on":"In: BHIB"
},
{
	"key":"H17_200A",
	"organism":"Sf",
	"specification":"Strain(s): 5348",
	"source":"Zaika_94",
	"details":"SfB01",
	"b_f":"Culture_medium",
	"meas_method":"plate_count",
	"condition":"NaCl(%):4, Nitrite(ppm):200, anaerobic",
	"temp":"28",
	"pH":"7.5",
	"aw":"0.977",
	"property":"",
	"tObs":"73",
	"logc":"0;3.02;6.5;3.15;22.5;5.79;27.5;5.6;47.5;7.55;51.5;7.42;73;7.33",
	"logcVar":"4.53",
	"spec_rate":"0.2634",
	"assumed":"aw",
	"comment":"",
	"in_on":"In: BHIB"
},
{
	"key":"H17_200B",
	"organism":"Sf",
	"specification":"Strain(s): 5348",
	"source":"Zaika_94",
	"details":"SfB01",
	"b_f":"Culture_medium",
	"meas_method":"plate_count",
	"condition":"NaCl(%):4, Nitrite(ppm):200, anaerobic",
	"temp":"28",
	"pH":"7.5",
	"aw":"0.977",
	"property":"",
	"tObs":"79",
	"logc":"0;3.03;6.5;3.16;22.5;5.77;27.5;5.07;47.5;7.54;51.5;7.53;73;7.72;79;7.72",
	"logcVar":"4.69",
	"spec_rate":"0.2356",
	"assumed":"aw",
	"comment":"",
	"in_on":"In: BHIB"
},
{
	"key":"H17_200C",
	"organism":"Sf",
	"specification":"Strain(s): 5348",
	"source":"Zaika_94",
	"details":"SfB01",
	"b_f":"Culture_medium",
	"meas_method":"plate_count",
	"condition":"NaCl(%):4, Nitrite(ppm):200, anaerobic",
	"temp":"28",
	"pH":"7.5",
	"aw":"0.977",
	"property":"",
	"tObs":"73",
	"logc":"0;3.03;6.5;3.08;22.5;5.96;27.5;5.33;47.5;7.61;51.5;7.53;73;7.48",
	"logcVar":"4.58",
	"spec_rate":"0.2572",
	"assumed":"aw",
	"comment":"",
	"in_on":"In: BHIB"
},
{
	"key":"H17_THA",
	"organism":"Sf",
	"specification":"Strain(s): 5348",
	"source":"Zaika_94",
	"details":"SfB01",
	"b_f":"Culture_medium",
	"meas_method":"plate_count",
	"condition":"NaCl(%):4, Nitrite(ppm):1000, anaerobic",
	"temp":"28",
	"pH":"7.5",
	"aw":"0.977",
	"property":"",
	"tObs":"73",
	"logc":"0;2.97;6.5;3.08;22.5;6;27.5;5.19;47.5;6.75;51.5;6.8;73;7.03",
	"logcVar":"4.06",
	"spec_rate":"0.1394",
	"assumed":"aw",
	"comment":"",
	"in_on":"In: BHIB"
},
{
	"key":"H17_THB",
	"organism":"Sf",
	"specification":"Strain(s): 5348",
	"source":"Zaika_94",
	"details":"SfB01",
	"b_f":"Culture_medium",
	"meas_method":"plate_count",
	"condition":"NaCl(%):4, Nitrite(ppm):1000, anaerobic",
	"temp":"28",
	"pH":"7.5",
	"aw":"0.977",
	"property":"",
	"tObs":"73",
	"logc":"0;3.03;6.5;3.09;22.5;6;27.5;5.32;47.5;6.97;51.5;8.35;73;7.46",
	"logcVar":"5.32",
	"spec_rate":"0.1659",
	"assumed":"aw",
	"comment":"",
	"in_on":"In: BHIB"
},
{
	"key":"H17_THC",
	"organism":"Sf",
	"specification":"Strain(s): 5348",
	"source":"Zaika_94",
	"details":"SfB01",
	"b_f":"Culture_medium",
	"meas_method":"plate_count",
	"condition":"NaCl(%):4, Nitrite(ppm):1000, anaerobic",
	"temp":"28",
	"pH":"7.5",
	"aw":"0.977",
	"property":"",
	"tObs":"73",
	"logc":"0;3.03;6.5;3.07;22.5;5.92;27.5;5.27;47.5;7.02;51.5;6.96;73;7.04",
	"logcVar":"4.01",
	"spec_rate":"0.248",
	"assumed":"aw",
	"comment":"",
	"in_on":"In: BHIB"
},
{
	"key":"H18_0A",
	"organism":"Sf",
	"specification":"Strain(s): 5348",
	"source":"Zaika_94",
	"details":"SfB01",
	"b_f":"Culture_medium",
	"meas_method":"plate_count",
	"condition":"NaCl(%):0.5, anaerobic",
	"temp":"37",
	"pH":"5.5",
	"aw":"0.997",
	"property":"",
	"tObs":"28",
	"logc":"0;3.06;2;2.95;4;3.93;7;4.98;19;7.78;22;8.02;25;7.72;28;7.8",
	"logcVar":"5.07",
	"spec_rate":"0.7062",
	"assumed":"aw",
	"comment":"",
	"in_on":"In: BHIB"
},
{
	"key":"H18_0B",
	"organism":"Sf",
	"specification":"Strain(s): 5348",
	"source":"Zaika_94",
	"details":"SfB01",
	"b_f":"Culture_medium",
	"meas_method":"plate_count",
	"condition":"NaCl(%):0.5, anaerobic",
	"temp":"37",
	"pH":"5.5",
	"aw":"0.997",
	"property":"",
	"tObs":"28",
	"logc":"0;3.08;2;3.01;4;3.66;7;4.87;19;7.7;22;7.78;25;7.54;28;7.69",
	"logcVar":"4.77",
	"spec_rate":"1.065",
	"assumed":"aw",
	"comment":"",
	"in_on":"In: BHIB"
},
{
	"key":"H18_0C",
	"organism":"Sf",
	"specification":"Strain(s): 5348",
	"source":"Zaika_94",
	"details":"SfB01",
	"b_f":"Culture_medium",
	"meas_method":"plate_count",
	"condition":"NaCl(%):0.5, anaerobic",
	"temp":"37",
	"pH":"5.5",
	"aw":"0.997",
	"property":"",
	"tObs":"28",
	"logc":"0;3.08;2;3.01;4;3.9;7;5.12;19;8.26;22;8.18;25;8.03;28;8.27",
	"logcVar":"5.26",
	"spec_rate":"1.062",
	"assumed":"aw",
	"comment":"",
	"in_on":"In: BHIB"
},
{
	"key":"H18_50B",
	"organism":"Sf",
	"specification":"Strain(s): 5348",
	"source":"Zaika_94",
	"details":"SfB01",
	"b_f":"Culture_medium",
	"meas_method":"plate_count",
	"condition":"NaCl(%):0.5, Nitrite(ppm):50, anaerobic",
	"temp":"37",
	"pH":"5.5",
	"aw":"0.997",
	"property":"",
	"tObs":"51",
	"logc":"0;2.98;2;3.09;4;3.09;7;3.04;19;4.04;22;4.33;25;4.53;28;4.73;43;8.29;46;8.17;51;8.24",
	"logcVar":"5.31",
	"spec_rate":"0.4845",
	"assumed":"aw",
	"comment":"",
	"in_on":"In: BHIB"
},
{
	"key":"H18_50C",
	"organism":"Sf",
	"specification":"Strain(s): 5348",
	"source":"Zaika_94",
	"details":"SfB01",
	"b_f":"Culture_medium",
	"meas_method":"plate_count",
	"condition":"NaCl(%):0.5, Nitrite(ppm):50, anaerobic",
	"temp":"37",
	"pH":"5.5",
	"aw":"0.997",
	"property":"",
	"tObs":"51",
	"logc":"0;3.05;2;2.98;4;3.09;7;3.43;19;5.47;22;5.7;25;6.2;28;7.13;43;8.39;46;8.26;51;8.48",
	"logcVar":"5.5",
	"spec_rate":"0.4304",
	"assumed":"aw",
	"comment":"",
	"in_on":"In: BHIB"
},
{
	"key":"H19_0A",
	"organism":"Sf",
	"specification":"Strain(s): 5348",
	"source":"Zaika_94",
	"details":"SfB01",
	"b_f":"Culture_medium",
	"meas_method":"plate_count",
	"condition":"NaCl(%):2.5, anaerobic",
	"temp":"37",
	"pH":"5.5",
	"aw":"0.986",
	"property":"",
	"tObs":"31",
	"logc":"0;3.02;5;4.38;7;5.06;10;6.5;24.5;8.15;28;8.16;31;8.16",
	"logcVar":"5.14",
	"spec_rate":"1.027",
	"assumed":"aw",
	"comment":"",
	"in_on":"In: BHIB"
},
{
	"key":"H19_0B",
	"organism":"Sf",
	"specification":"Strain(s): 5348",
	"source":"Zaika_94",
	"details":"SfB01",
	"b_f":"Culture_medium",
	"meas_method":"plate_count",
	"condition":"NaCl(%):2.5, anaerobic",
	"temp":"37",
	"pH":"5.5",
	"aw":"0.986",
	"property":"",
	"tObs":"31",
	"logc":"0;2.97;5;4.17;7;4.76;10;6.3;24.5;7.65;28;7.92;31;7.92",
	"logcVar":"4.95",
	"spec_rate":"0.7417",
	"assumed":"aw",
	"comment":"",
	"in_on":"In: BHIB"
},
{
	"key":"H19_0C",
	"organism":"Sf",
	"specification":"Strain(s): 5348",
	"source":"Zaika_94",
	"details":"SfB01",
	"b_f":"Culture_medium",
	"meas_method":"plate_count",
	"condition":"NaCl(%):2.5, anaerobic",
	"temp":"37",
	"pH":"5.5",
	"aw":"0.986",
	"property":"",
	"tObs":"31",
	"logc":"0;2.97;5;4.32;7;4.81;10;6.61;24.5;7.7;28;7.79;31;7.79",
	"logcVar":"4.82",
	"spec_rate":"0.8022",
	"assumed":"aw",
	"comment":"",
	"in_on":"In: BHIB"
},
{
	"key":"H19_100C",
	"organism":"Sf",
	"specification":"Strain(s): 5348",
	"source":"Zaika_94",
	"details":"SfB01",
	"b_f":"Culture_medium",
	"meas_method":"plate_count",
	"condition":"NaCl(%):2.5, Nitrite(ppm):100, anaerobic",
	"temp":"37",
	"pH":"5.5",
	"aw":"0.986",
	"property":"",
	"tObs":"73.25",
	"logc":"0;2.97;5;3.06;10;3.16;24.5;4.36;28;4.73;31;4.82;49;7.77;52.25;7.86;73.25;7.86",
	"logcVar":"4.89",
	"spec_rate":"0.3707",
	"assumed":"aw",
	"comment":"",
	"in_on":"In: BHIB"
},
{
	"key":"H19_50A",
	"organism":"Sf",
	"specification":"Strain(s): 5348",
	"source":"Zaika_94",
	"details":"SfB01",
	"b_f":"Culture_medium",
	"meas_method":"plate_count",
	"condition":"NaCl(%):2.5, Nitrite(ppm):50, anaerobic",
	"temp":"37",
	"pH":"5.5",
	"aw":"0.986",
	"property":"",
	"tObs":"31",
	"logc":"0;2.97;5;2.92;7;3.22;10;3.98;24.5;8.21;28;8.34;31;8.34",
	"logcVar":"5.42",
	"spec_rate":"0.8273",
	"assumed":"aw",
	"comment":"",
	"in_on":"In: BHIB"
},
{
	"key":"H19_50B",
	"organism":"Sf",
	"specification":"Strain(s): 5348",
	"source":"Zaika_94",
	"details":"SfB01",
	"b_f":"Culture_medium",
	"meas_method":"plate_count",
	"condition":"NaCl(%):2.5, Nitrite(ppm):50, anaerobic",
	"temp":"37",
	"pH":"5.5",
	"aw":"0.986",
	"property":"",
	"tObs":"31",
	"logc":"0;2.97;5;3.01;7;3.13;10;3.76;24.5;7.98;28;7.96;31;7.96",
	"logcVar":"5.01",
	"spec_rate":"1.084",
	"assumed":"aw",
	"comment":"",
	"in_on":"In: BHIB"
},
{
	"key":"H2_100A",
	"organism":"Sf",
	"specification":"Strain(s): 5348",
	"source":"Zaika_94",
	"details":"SfB01",
	"b_f":"Culture_medium",
	"meas_method":"plate_count",
	"condition":"NaCl(%):4, Nitrite(ppm):100, anaerobic",
	"temp":"28",
	"pH":"6",
	"aw":"0.977",
	"property":"",
	"tObs":"241",
	"logc":"0;2.54;49;2.63;100;3.15;145;5.46;168;8;193;7.87;215;7.87;241;7.87",
	"logcVar":"5.46",
	"spec_rate":"0.131",
	"assumed":"aw",
	"comment":"",
	"in_on":"In: BHIB"
},
{
	"key":"H2_100B",
	"organism":"Sf",
	"specification":"Strain(s): 5348",
	"source":"Zaika_94",
	"details":"SfB01",
	"b_f":"Culture_medium",
	"meas_method":"plate_count",
	"condition":"NaCl(%):4, Nitrite(ppm):100, anaerobic",
	"temp":"28",
	"pH":"6",
	"aw":"0.977",
	"property":"",
	"tObs":"359.5",
	"logc":"0;2.57;24;2.76;33;2.75;49;2.73;100;3.03;241;4.56;313;7.74;337.5;7.5;359.5;7.5",
	"logcVar":"5.17",
	"spec_rate":"0.06053",
	"assumed":"aw",
	"comment":"",
	"in_on":"In: BHIB"
},
{
	"key":"H2_50A",
	"organism":"Sf",
	"specification":"Strain(s): 5348",
	"source":"Zaika_94",
	"details":"SfB01",
	"b_f":"Culture_medium",
	"meas_method":"plate_count",
	"condition":"NaCl(%):4, Nitrite(ppm):50, anaerobic",
	"temp":"28",
	"pH":"6",
	"aw":"0.977",
	"property":"",
	"tObs":"168",
	"logc":"0;2.72;6;2.81;8;2.9;24;4.09;30;4.53;33;4.63;49;5.2;53.5;5.7;100;8.43;145;8.3;168;8.08",
	"logcVar":"5.71",
	"spec_rate":"0.1405",
	"assumed":"aw",
	"comment":"",
	"in_on":"In: BHIB"
},
{
	"key":"H2_50B",
	"organism":"Sf",
	"specification":"Strain(s): 5348",
	"source":"Zaika_94",
	"details":"SfB01",
	"b_f":"Culture_medium",
	"meas_method":"plate_count",
	"condition":"NaCl(%):4, Nitrite(ppm):50, anaerobic",
	"temp":"28",
	"pH":"6",
	"aw":"0.977",
	"property":"",
	"tObs":"145",
	"logc":"0;2.89;6;2.83;8;2.96;24;4.78;30;4.69;33;5.12;49;7.42;53.5;7.64;100;8;145;8",
	"logcVar":"5.17",
	"spec_rate":"0.2901",
	"assumed":"aw",
	"comment":"",
	"in_on":"In: BHIB"
},
{
	"key":"H20_0A",
	"organism":"Sf",
	"specification":"Strain(s): 5348",
	"source":"Zaika_94",
	"details":"SfB01",
	"b_f":"Culture_medium",
	"meas_method":"plate_count",
	"condition":"NaCl(%):4, anaerobic",
	"temp":"37",
	"pH":"5.5",
	"aw":"0.977",
	"property":"",
	"tObs":"48",
	"logc":"0;2.89;3;2.9;6;3.61;8.5;4.43;10.5;4.69;24;6.97;27;6.92;30;6.93;36;6.82;48;6.82",
	"logcVar":"4.08",
	"spec_rate":"0.6164",
	"assumed":"aw",
	"comment":"",
	"in_on":"In: BHIB"
},
{
	"key":"H20_0B",
	"organism":"Sf",
	"specification":"Strain(s): 5348",
	"source":"Zaika_94",
	"details":"SfB01",
	"b_f":"Culture_medium",
	"meas_method":"plate_count",
	"condition":"NaCl(%):4, anaerobic",
	"temp":"37",
	"pH":"5.5",
	"aw":"0.977",
	"property":"",
	"tObs":"48",
	"logc":"0;2.87;3;2.82;6;3.68;8.5;4.46;10.5;4.79;24;8.38;27;8.57;30;8.64;36;8.53;48;8.53",
	"logcVar":"5.82",
	"spec_rate":"0.7067",
	"assumed":"aw",
	"comment":"",
	"in_on":"In: BHIB"
},
{
	"key":"H20_0C",
	"organism":"Sf",
	"specification":"Strain(s): 5348",
	"source":"Zaika_94",
	"details":"SfB01",
	"b_f":"Culture_medium",
	"meas_method":"plate_count",
	"condition":"NaCl(%):4, anaerobic",
	"temp":"37",
	"pH":"5.5",
	"aw":"0.977",
	"property":"",
	"tObs":"48",
	"logc":"0;2.84;3;2.91;6;3.64;8.5;4.47;10.5;4.74;24;7.54;27;7.53;30;7.54;36;7.61;48;7.61",
	"logcVar":"4.77",
	"spec_rate":"0.6208",
	"assumed":"aw",
	"comment":"",
	"in_on":"In: BHIB"
},
{
	"key":"H21_0A",
	"organism":"Sf",
	"specification":"Strain(s): 5348",
	"source":"Zaika_94",
	"details":"SfB01",
	"b_f":"Culture_medium",
	"meas_method":"plate_count",
	"condition":"NaCl(%):0.5, anaerobic",
	"temp":"37",
	"pH":"6.5",
	"aw":"0.997",
	"property":"",
	"tObs":"32.5",
	"logc":"0;3.03;3;4.1;5;5.22;6.5;6.68;8.5;7.54;12;8.47;24;8.54;26;8.56;30.5;8.55;32.5;8.55",
	"logcVar":"5.53",
	"spec_rate":"1.59",
	"assumed":"aw",
	"comment":"",
	"in_on":"In: BHIB"
},
{
	"key":"H21_0B",
	"organism":"Sf",
	"specification":"Strain(s): 5348",
	"source":"Zaika_94",
	"details":"SfB01",
	"b_f":"Culture_medium",
	"meas_method":"plate_count",
	"condition":"NaCl(%):0.5, anaerobic",
	"temp":"37",
	"pH":"6.5",
	"aw":"0.997",
	"property":"",
	"tObs":"32.5",
	"logc":"0;3.02;3;4;5;5.13;6.5;6.6;8.5;7.55;12;8.41;24;8.47;26;8.44;30.5;8.5;32.5;8.5",
	"logcVar":"5.48",
	"spec_rate":"1.655",
	"assumed":"aw",
	"comment":"",
	"in_on":"In: BHIB"
},
{
	"key":"H21_0C",
	"organism":"Sf",
	"specification":"Strain(s): 5348",
	"source":"Zaika_94",
	"details":"SfB01",
	"b_f":"Culture_medium",
	"meas_method":"plate_count",
	"condition":"NaCl(%):0.5, anaerobic",
	"temp":"37",
	"pH":"6.5",
	"aw":"0.997",
	"property":"",
	"tObs":"32.5",
	"logc":"0;2.97;3;4.13;5;5.15;6.5;6.71;8.5;7.69;12;8.56;24;8.81;26;8.74;30.5;8.71;32.5;8.76",
	"logcVar":"5.84",
	"spec_rate":"1.655",
	"assumed":"aw",
	"comment":"",
	"in_on":"In: BHIB"
},
{
	"key":"H21_200A",
	"organism":"Sf",
	"specification":"Strain(s): 5348",
	"source":"Zaika_94",
	"details":"SfB01",
	"b_f":"Culture_medium",
	"meas_method":"plate_count",
	"condition":"NaCl(%):0.5, Nitrite(ppm):200, anaerobic",
	"temp":"37",
	"pH":"6.5",
	"aw":"0.997",
	"property":"",
	"tObs":"32.5",
	"logc":"0;2.91;3;3.94;5;4.84;6.5;6.06;8.5;7.51;12;8.13;24;8.44;26;8.44;30.5;8.39;32.5;8.37",
	"logcVar":"5.53",
	"spec_rate":"1.69",
	"assumed":"aw",
	"comment":"",
	"in_on":"In: BHIB"
},
{
	"key":"H21_200B",
	"organism":"Sf",
	"specification":"Strain(s): 5348",
	"source":"Zaika_94",
	"details":"SfB01",
	"b_f":"Culture_medium",
	"meas_method":"plate_count",
	"condition":"NaCl(%):0.5, Nitrite(ppm):200, anaerobic",
	"temp":"37",
	"pH":"6.5",
	"aw":"0.997",
	"property":"",
	"tObs":"32.5",
	"logc":"0;2.96;3;3.84;5;4.76;6.5;5.86;8.5;6.92;12;8.24;24;8.49;26;8.52;30.5;8.49;32.5;8.49",
	"logcVar":"5.56",
	"spec_rate":"1.374",
	"assumed":"aw",
	"comment":"",
	"in_on":"In: BHIB"
},
{
	"key":"H21_200C",
	"organism":"Sf",
	"specification":"Strain(s): 5348",
	"source":"Zaika_94",
	"details":"SfB01",
	"b_f":"Culture_medium",
	"meas_method":"plate_count",
	"condition":"NaCl(%):0.5, Nitrite(ppm):200, anaerobic",
	"temp":"37",
	"pH":"6.5",
	"aw":"0.997",
	"property":"",
	"tObs":"32.5",
	"logc":"0;2.92;3;3.83;5;4.89;6.5;6.02;8.5;7.4;12;8.16;24;8.47;26;8.54;30.5;8.48;32.5;8.48",
	"logcVar":"5.62",
	"spec_rate":"1.621",
	"assumed":"aw",
	"comment":"",
	"in_on":"In: BHIB"
},
{
	"key":"H22_0A",
	"organism":"Sf",
	"specification":"Strain(s): 5348",
	"source":"Zaika_94",
	"details":"SfB01",
	"b_f":"Culture_medium",
	"meas_method":"plate_count",
	"condition":"NaCl(%):2.5, anaerobic",
	"temp":"37",
	"pH":"6.5",
	"aw":"0.986",
	"property":"",
	"tObs":"30.5",
	"logc":"0;2.84;3;3.46;5;4.72;6.5;5.32;11.25;8.28;13.25;8.43;24;8.4;26;8.61;29;8.23;30.5;8.39",
	"logcVar":"5.77",
	"spec_rate":"1.559",
	"assumed":"aw",
	"comment":"",
	"in_on":"In: BHIB"
},
{
	"key":"H22_0B",
	"organism":"Sf",
	"specification":"Strain(s): 5348",
	"source":"Zaika_94",
	"details":"SfB01",
	"b_f":"Culture_medium",
	"meas_method":"plate_count",
	"condition":"NaCl(%):2.5, anaerobic",
	"temp":"37",
	"pH":"6.5",
	"aw":"0.986",
	"property":"",
	"tObs":"30.5",
	"logc":"0;2.71;3;3.5;5;4.76;6.5;5.06;11.25;8.02;13.25;8.16;24;8.36;26;8.56;29;8.32;30.5;8.53",
	"logcVar":"5.85",
	"spec_rate":"1.352",
	"assumed":"aw",
	"comment":"",
	"in_on":"In: BHIB"
},
{
	"key":"H22_0C",
	"organism":"Sf",
	"specification":"Strain(s): 5348",
	"source":"Zaika_94",
	"details":"SfB01",
	"b_f":"Culture_medium",
	"meas_method":"plate_count",
	"condition":"NaCl(%):2.5, anaerobic",
	"temp":"37",
	"pH":"6.5",
	"aw":"0.986",
	"property":"",
	"tObs":"30.5",
	"logc":"0;2.75;3;3.56;5;4.71;6.5;4.99;11.25;8.13;13.25;8.42;24;8.42;26;8.25;29;8.28;30.5;8.35",
	"logcVar":"5.67",
	"spec_rate":"1.467",
	"assumed":"aw",
	"comment":"",
	"in_on":"In: BHIB"
},
{
	"key":"H22_200A",
	"organism":"Sf",
	"specification":"Strain(s): 5348",
	"source":"Zaika_94",
	"details":"SfB01",
	"b_f":"Culture_medium",
	"meas_method":"plate_count",
	"condition":"NaCl(%):2.5, Nitrite(ppm):200, anaerobic",
	"temp":"37",
	"pH":"6.5",
	"aw":"0.986",
	"property":"",
	"tObs":"30.5",
	"logc":"0;2.89;3;3.42;5;4.42;6.5;4.68;11.25;7.33;13.25;8.54;24;8.09;26;8.01;29;8.04;30.5;8.07",
	"logcVar":"5.65",
	"spec_rate":"1.321",
	"assumed":"aw",
	"comment":"",
	"in_on":"In: BHIB"
},
{
	"key":"H22_200B",
	"organism":"Sf",
	"specification":"Strain(s): 5348",
	"source":"Zaika_94",
	"details":"SfB01",
	"b_f":"Culture_medium",
	"meas_method":"plate_count",
	"condition":"NaCl(%):2.5, Nitrite(ppm):200, anaerobic",
	"temp":"37",
	"pH":"6.5",
	"aw":"0.986",
	"property":"",
	"tObs":"30.5",
	"logc":"0;2.72;3;3.47;5;4.62;6.5;4.71;11.25;6.87;13.25;8.11;24;8.12;26;8.03;29;7.97;30.5;7.93",
	"logcVar":"5.4",
	"spec_rate":"0.9514",
	"assumed":"aw",
	"comment":"",
	"in_on":"In: BHIB"
},
{
	"key":"H22_200C",
	"organism":"Sf",
	"specification":"Strain(s): 5348",
	"source":"Zaika_94",
	"details":"SfB01",
	"b_f":"Culture_medium",
	"meas_method":"plate_count",
	"condition":"NaCl(%):2.5, Nitrite(ppm):200, anaerobic",
	"temp":"37",
	"pH":"6.5",
	"aw":"0.986",
	"property":"",
	"tObs":"30.5",
	"logc":"0;2.71;3;3.47;5;4.6;6.5;5.34;11.25;6.76;13.25;7.5;24;8.15;26;8.05;29;7.91;30.5;7.99",
	"logcVar":"5.44",
	"spec_rate":"0.8856",
	"assumed":"aw",
	"comment":"",
	"in_on":"In: BHIB"
},
{
	"key":"H23_0A",
	"organism":"Sf",
	"specification":"Strain(s): 5348",
	"source":"Zaika_94",
	"details":"SfB01",
	"b_f":"Culture_medium",
	"meas_method":"plate_count",
	"condition":"NaCl(%):4, anaerobic",
	"temp":"37",
	"pH":"6.5",
	"aw":"0.977",
	"property":"",
	"tObs":"33.75",
	"logc":"0;3.16;2.5;3.2;4;3.2;9.25;4.49;11;4.94;23.25;7.3;29;7.4;33.75;7.32",
	"logcVar":"4.24",
	"spec_rate":"0.677",
	"assumed":"aw",
	"comment":"",
	"in_on":"In: BHIB"
},
{
	"key":"H23_0B",
	"organism":"Sf",
	"specification":"Strain(s): 5348",
	"source":"Zaika_94",
	"details":"SfB01",
	"b_f":"Culture_medium",
	"meas_method":"plate_count",
	"condition":"NaCl(%):4, anaerobic",
	"temp":"37",
	"pH":"6.5",
	"aw":"0.977",
	"property":"",
	"tObs":"33.75",
	"logc":"0;3.13;2.5;3.12;4;3.38;9.25;4.58;11;4.8;23.25;7.65;29;7.48;33.75;7.48",
	"logcVar":"4.53",
	"spec_rate":"0.6767",
	"assumed":"aw",
	"comment":"",
	"in_on":"In: BHIB"
},
{
	"key":"H23_0C",
	"organism":"Sf",
	"specification":"Strain(s): 5348",
	"source":"Zaika_94",
	"details":"SfB01",
	"b_f":"Culture_medium",
	"meas_method":"plate_count",
	"condition":"NaCl(%):4, anaerobic",
	"temp":"37",
	"pH":"6.5",
	"aw":"0.977",
	"property":"",
	"tObs":"33.75",
	"logc":"0;3.17;2.5;3.24;4;3.26;9.25;4.92;11;5.62;23.25;8.26;29;8.01;33.75;8.01",
	"logcVar":"5.09",
	"spec_rate":"0.9982",
	"assumed":"aw",
	"comment":"",
	"in_on":"In: BHIB"
},
{
	"key":"H23_100A",
	"organism":"Sf",
	"specification":"Strain(s): 5348",
	"source":"Zaika_94",
	"details":"SfB01",
	"b_f":"Culture_medium",
	"meas_method":"plate_count",
	"condition":"NaCl(%):4, Nitrite(ppm):100, anaerobic",
	"temp":"37",
	"pH":"6.5",
	"aw":"0.977",
	"property":"",
	"tObs":"33.75",
	"logc":"0;3.17;2.5;3.21;4;3.31;9.25;5.04;11;5.66;23.25;8.03;33.75;8.03",
	"logcVar":"4.86",
	"spec_rate":"0.9411",
	"assumed":"aw",
	"comment":"",
	"in_on":"In: BHIB"
},
{
	"key":"H23_100B",
	"organism":"Sf",
	"specification":"Strain(s): 5348",
	"source":"Zaika_94",
	"details":"SfB01",
	"b_f":"Culture_medium",
	"meas_method":"plate_count",
	"condition":"NaCl(%):4, Nitrite(ppm):100, anaerobic",
	"temp":"37",
	"pH":"6.5",
	"aw":"0.977",
	"property":"",
	"tObs":"80.75",
	"logc":"0;3.16;2.5;3.23;4;3.24;9.25;3.58;11;3.81;23.25;3.62;29;4.1;33.75;4.96;52;6.49;80.75;6.49",
	"logcVar":"3.33",
	"spec_rate":"0.4198",
	"assumed":"aw",
	"comment":"",
	"in_on":"In: BHIB"
},
{
	"key":"H23_100C",
	"organism":"Sf",
	"specification":"Strain(s): 5348",
	"source":"Zaika_94",
	"details":"SfB01",
	"b_f":"Culture_medium",
	"meas_method":"plate_count",
	"condition":"NaCl(%):4, Nitrite(ppm):100, anaerobic",
	"temp":"37",
	"pH":"6.5",
	"aw":"0.977",
	"property":"",
	"tObs":"33.75",
	"logc":"0;3.15;2.5;3.15;4;3.29;9.25;4.91;11;5.55;23.25;7.72;29;7.49;33.75;7.49",
	"logcVar":"4.57",
	"spec_rate":"0.907",
	"assumed":"aw",
	"comment":"",
	"in_on":"In: BHIB"
},
{
	"key":"H24_0A",
	"organism":"Sf",
	"specification":"Strain(s): 5348",
	"source":"Zaika_94",
	"details":"SfB01",
	"b_f":"Culture_medium",
	"meas_method":"plate_count",
	"condition":"NaCl(%):0.5, anaerobic",
	"temp":"37",
	"pH":"7.5",
	"aw":"0.997",
	"property":"",
	"tObs":"30.5",
	"logc":"0;3;3;4.2;5;5.3;6.5;6.72;11.5;8.85;13.5;9.07;24;8.82;26;8.84;30.5;8.81",
	"logcVar":"6.07",
	"spec_rate":"1.817",
	"assumed":"aw",
	"comment":"",
	"in_on":"In: BHIB"
},
{
	"key":"H24_0B",
	"organism":"Sf",
	"specification":"Strain(s): 5348",
	"source":"Zaika_94",
	"details":"SfB01",
	"b_f":"Culture_medium",
	"meas_method":"plate_count",
	"condition":"NaCl(%):0.5, anaerobic",
	"temp":"37",
	"pH":"7.5",
	"aw":"0.997",
	"property":"",
	"tObs":"30.5",
	"logc":"0;2.92;3;4.33;5;5.49;6.5;6.73;11.5;8.65;13.5;8.84;24;8.79;26;8.65;30.5;8.82",
	"logcVar":"5.92",
	"spec_rate":"1.625",
	"assumed":"aw",
	"comment":"",
	"in_on":"In: BHIB"
},
{
	"key":"H24_0C",
	"organism":"Sf",
	"specification":"Strain(s): 5348",
	"source":"Zaika_94",
	"details":"SfB01",
	"b_f":"Culture_medium",
	"meas_method":"plate_count",
	"condition":"NaCl(%):0.5, anaerobic",
	"temp":"37",
	"pH":"7.5",
	"aw":"0.997",
	"property":"",
	"tObs":"30.5",
	"logc":"0;2.98;3;4.17;5;5.28;6.5;6.81;11.5;8.89;13.5;8.82;24;8.92;26;8.75;30.5;8.9",
	"logcVar":"5.94",
	"spec_rate":"1.913",
	"assumed":"aw",
	"comment":"",
	"in_on":"In: BHIB"
},
{
	"key":"H24_200A",
	"organism":"Sf",
	"specification":"Strain(s): 5348",
	"source":"Zaika_94",
	"details":"SfB01",
	"b_f":"Culture_medium",
	"meas_method":"plate_count",
	"condition":"NaCl(%):0.5, Nitrite(ppm):200, anaerobic",
	"temp":"37",
	"pH":"7.5",
	"aw":"0.997",
	"property":"",
	"tObs":"30.5",
	"logc":"0;2.93;3;4.25;5;5.02;6.5;6.28;11.5;9.02;13.5;9.24;24;8.96;26;9.1;30.5;9.2",
	"logcVar":"6.31",
	"spec_rate":"1.621",
	"assumed":"aw",
	"comment":"",
	"in_on":"In: BHIB"
},
{
	"key":"H24_200B",
	"organism":"Sf",
	"specification":"Strain(s): 5348",
	"source":"Zaika_94",
	"details":"SfB01",
	"b_f":"Culture_medium",
	"meas_method":"plate_count",
	"condition":"NaCl(%):0.5, Nitrite(ppm):200, anaerobic",
	"temp":"37",
	"pH":"7.5",
	"aw":"0.997",
	"property":"",
	"tObs":"30.5",
	"logc":"0;2.88;3;4.16;5;5.14;6.5;6.76;11.5;8.83;13.5;8.91;24;8.95;26;8.72;30.5;8.76",
	"logcVar":"6.07",
	"spec_rate":"1.907",
	"assumed":"aw",
	"comment":"",
	"in_on":"In: BHIB"
},
{
	"key":"H24_200C",
	"organism":"Sf",
	"specification":"Strain(s): 5348",
	"source":"Zaika_94",
	"details":"SfB01",
	"b_f":"Culture_medium",
	"meas_method":"plate_count",
	"condition":"NaCl(%):0.5, Nitrite(ppm):200, anaerobic",
	"temp":"37",
	"pH":"7.5",
	"aw":"0.997",
	"property":"",
	"tObs":"30.5",
	"logc":"0;2.94;3;4.15;5;5.21;6.5;6.7;11.5;8.79;13.5;8.73;24;8.68;26;8.95;30.5;8.91",
	"logcVar":"6.01",
	"spec_rate":"1.833",
	"assumed":"aw",
	"comment":"",
	"in_on":"In: BHIB"
},
{
	"key":"H25_0A",
	"organism":"Sf",
	"specification":"Strain(s): 5348",
	"source":"Zaika_94",
	"details":"SfB01",
	"b_f":"Culture_medium",
	"meas_method":"plate_count",
	"condition":"NaCl(%):0.5, anaerobic",
	"temp":"19",
	"pH":"5.5",
	"aw":"0.997",
	"property":"",
	"tObs":"240.8",
	"logc":"0;2.9;23.5;2.54;47.25;2.13;141;4.73;168;6.71;190;8.32;217.5;8.29;240.75;8.43",
	"logcVar":"6.3",
	"spec_rate":"0.1915",
	"assumed":"aw",
	"comment":"",
	"in_on":"In: BHIB"
},
{
	"key":"H25_0B",
	"organism":"Sf",
	"specification":"Strain(s): 5348",
	"source":"Zaika_94",
	"details":"SfB01",
	"b_f":"Culture_medium",
	"meas_method":"plate_count",
	"condition":"NaCl(%):0.5, anaerobic",
	"temp":"19",
	"pH":"5.5",
	"aw":"0.997",
	"property":"",
	"tObs":"312",
	"logc":"0;2.95;23.5;2.68;47.25;2.49;141;3.83;168;5.16;190;6.83;217.5;8.42;240.75;8.37;312;8.38",
	"logcVar":"5.93",
	"spec_rate":"0.1618",
	"assumed":"aw",
	"comment":"",
	"in_on":"In: BHIB"
},
{
	"key":"H26_0A",
	"organism":"Sf",
	"specification":"Strain(s): 5348",
	"source":"Zaika_94",
	"details":"SfB01",
	"b_f":"Culture_medium",
	"meas_method":"plate_count",
	"condition":"NaCl(%):2.5, anaerobic",
	"temp":"19",
	"pH":"5.5",
	"aw":"0.986",
	"property":"",
	"tObs":"304.5",
	"logc":"0;2.86;66;2.22;168.5;3.6;256;7.76;282;7.83;304.5;7.7",
	"logcVar":"5.61",
	"spec_rate":"0.04633",
	"assumed":"aw",
	"comment":"",
	"in_on":"In: BHIB"
},
{
	"key":"H27_0A",
	"organism":"Sf",
	"specification":"Strain(s): 5348",
	"source":"Zaika_94",
	"details":"SfB01",
	"b_f":"Culture_medium",
	"meas_method":"plate_count",
	"condition":"NaCl(%):0.5, anaerobic",
	"temp":"19",
	"pH":"6.5",
	"aw":"0.997",
	"property":"",
	"tObs":"120.5",
	"logc":"0;2.77;18;4.68;24;4.76;96;8.72;99;8.79;114;8.79;120.5;9.02",
	"logcVar":"6.25",
	"spec_rate":"0.2021",
	"assumed":"aw",
	"comment":"",
	"in_on":"In: BHIB"
},
{
	"key":"H27_0B",
	"organism":"Sf",
	"specification":"Strain(s): 5348",
	"source":"Zaika_94",
	"details":"SfB01",
	"b_f":"Culture_medium",
	"meas_method":"plate_count",
	"condition":"NaCl(%):0.5, anaerobic",
	"temp":"19",
	"pH":"6.5",
	"aw":"0.997",
	"property":"",
	"tObs":"120.5",
	"logc":"0;2.74;18;4.6;24;4.67;96;8.6;99;8.72;114;8.46;120.5;8.63",
	"logcVar":"5.98",
	"spec_rate":"0.198",
	"assumed":"aw",
	"comment":"",
	"in_on":"In: BHIB"
},
{
	"key":"H27_0C",
	"organism":"Sf",
	"specification":"Strain(s): 5348",
	"source":"Zaika_94",
	"details":"SfB01",
	"b_f":"Culture_medium",
	"meas_method":"plate_count",
	"condition":"NaCl(%):0.5, anaerobic",
	"temp":"19",
	"pH":"6.5",
	"aw":"0.997",
	"property":"",
	"tObs":"120.5",
	"logc":"0;2.68;18;4.73;24;4.71;96;8.36;99;8.28;114;8.32;120.5;8.28",
	"logcVar":"5.68",
	"spec_rate":"0.2105",
	"assumed":"aw",
	"comment":"",
	"in_on":"In: BHIB"
},
{
	"key":"H27_100A",
	"organism":"Sf",
	"specification":"Strain(s): 5348",
	"source":"Zaika_94",
	"details":"SfB01",
	"b_f":"Culture_medium",
	"meas_method":"plate_count",
	"condition":"NaCl(%):0.5, Nitrite(ppm):100, anaerobic",
	"temp":"19",
	"pH":"6.5",
	"aw":"0.997",
	"property":"",
	"tObs":"120.5",
	"logc":"0;2.65;18;4.27;24;4.39;96;8;99;8;114;7.88;120.5;7.98",
	"logcVar":"5.35",
	"spec_rate":"0.1769",
	"assumed":"aw",
	"comment":"",
	"in_on":"In: BHIB"
},
{
	"key":"H27_100B",
	"organism":"Sf",
	"specification":"Strain(s): 5348",
	"source":"Zaika_94",
	"details":"SfB01",
	"b_f":"Culture_medium",
	"meas_method":"plate_count",
	"condition":"NaCl(%):0.5, Nitrite(ppm):100, anaerobic",
	"temp":"19",
	"pH":"6.5",
	"aw":"0.997",
	"property":"",
	"tObs":"120.5",
	"logc":"0;2.65;18;3.85;24;3.91;96;8.26;99;8.45;114;8.59;120.5;8.34",
	"logcVar":"5.94",
	"spec_rate":"0.1507",
	"assumed":"aw",
	"comment":"",
	"in_on":"In: BHIB"
},
{
	"key":"H27_100C",
	"organism":"Sf",
	"specification":"Strain(s): 5348",
	"source":"Zaika_94",
	"details":"SfB01",
	"b_f":"Culture_medium",
	"meas_method":"plate_count",
	"condition":"NaCl(%):0.5, Nitrite(ppm):100, anaerobic",
	"temp":"19",
	"pH":"6.5",
	"aw":"0.997",
	"property":"",
	"tObs":"120.5",
	"logc":"0;2.83;18;4.27;24;4.17;96;8.29;99;8.31;114;8.22;120.5;8.32",
	"logcVar":"5.49",
	"spec_rate":"0.1515",
	"assumed":"aw",
	"comment":"",
	"in_on":"In: BHIB"
},
{
	"key":"H27_200A",
	"organism":"Sf",
	"specification":"Strain(s): 5348",
	"source":"Zaika_94",
	"details":"SfB01",
	"b_f":"Culture_medium",
	"meas_method":"plate_count",
	"condition":"NaCl(%):0.5, Nitrite(ppm):200, anaerobic",
	"temp":"19",
	"pH":"6.5",
	"aw":"0.997",
	"property":"",
	"tObs":"164.5",
	"logc":"0;2.67;18;3.68;24;3.74;96;6.38;114;6.73;120;6.65;141.5;6.98;164.5;7.4",
	"logcVar":"4.73",
	"spec_rate":"0.08179",
	"assumed":"aw",
	"comment":"",
	"in_on":"In: BHIB"
},
{
	"key":"H27_200B",
	"organism":"Sf",
	"specification":"Strain(s): 5348",
	"source":"Zaika_94",
	"details":"SfB01",
	"b_f":"Culture_medium",
	"meas_method":"plate_count",
	"condition":"NaCl(%):0.5, Nitrite(ppm):200, anaerobic",
	"temp":"19",
	"pH":"6.5",
	"aw":"0.997",
	"property":"",
	"tObs":"164.5",
	"logc":"0;2.42;18;3.75;24;3.83;96;7.4;114;7.69;120;7.58;141.5;7.89;164.5;7.83",
	"logcVar":"5.47",
	"spec_rate":"0.1259",
	"assumed":"aw",
	"comment":"",
	"in_on":"In: BHIB"
},
{
	"key":"H27_200C",
	"organism":"Sf",
	"specification":"Strain(s): 5348",
	"source":"Zaika_94",
	"details":"SfB01",
	"b_f":"Culture_medium",
	"meas_method":"plate_count",
	"condition":"NaCl(%):0.5, Nitrite(ppm):200, anaerobic",
	"temp":"19",
	"pH":"6.5",
	"aw":"0.997",
	"property":"",
	"tObs":"164.5",
	"logc":"0;2.56;18;3.75;24;3.84;96;7.64;114;8;141.5;8.03;164.5;8.13",
	"logcVar":"5.57",
	"spec_rate":"0.1288",
	"assumed":"aw",
	"comment":"",
	"in_on":"In: BHIB"
},
{
	"key":"H28_0A",
	"organism":"Sf",
	"specification":"Strain(s): 5348",
	"source":"Zaika_94",
	"details":"SfB01",
	"b_f":"Culture_medium",
	"meas_method":"plate_count",
	"condition":"NaCl(%):2.5, anaerobic",
	"temp":"19",
	"pH":"6.5",
	"aw":"0.986",
	"property":"",
	"tObs":"336",
	"logc":"0;2.1;48;2.51;73;3.35;93;3.54;99;3.63;166.5;5.92;191;6.86;214.5;7.52;238.5;7.55;263;7.62;336;7.62",
	"logcVar":"5.52",
	"spec_rate":"0.08068",
	"assumed":"aw",
	"comment":"",
	"in_on":"In: BHIB"
},
{
	"key":"H28_0B",
	"organism":"Sf",
	"specification":"Strain(s): 5348",
	"source":"Zaika_94",
	"details":"SfB01",
	"b_f":"Culture_medium",
	"meas_method":"plate_count",
	"condition":"NaCl(%):2.5, anaerobic",
	"temp":"19",
	"pH":"6.5",
	"aw":"0.986",
	"property":"",
	"tObs":"385.5",
	"logc":"0;2.1;48;2.43;73;3.28;93;3.47;99;3.36;166.5;4.52;191;4.95;214.5;5.36;238.5;5.7;263;6.07;336;7.16;361;7.65;385.5;7.63",
	"logcVar":"5.55",
	"spec_rate":"0.03516",
	"assumed":"aw",
	"comment":"",
	"in_on":"In: BHIB"
},
{
	"key":"H29_0A",
	"organism":"Sf",
	"specification":"Strain(s): 5348",
	"source":"Zaika_94",
	"details":"SfB01",
	"b_f":"Culture_medium",
	"meas_method":"plate_count",
	"condition":"NaCl(%):4, anaerobic",
	"temp":"19",
	"pH":"6.5",
	"aw":"0.977",
	"property":"",
	"tObs":"315.5",
	"logc":"0;3.08;70.5;3.41;95;3.31;118.5;3.15;142.5;3.51;167;4.09;240.5;6.09;265.5;6.72;290;7.32;315.5;7.19",
	"logcVar":"4.24",
	"spec_rate":"0.06945",
	"assumed":"aw",
	"comment":"",
	"in_on":"In: BHIB"
},
{
	"key":"H29_0B",
	"organism":"Sf",
	"specification":"Strain(s): 5348",
	"source":"Zaika_94",
	"details":"SfB01",
	"b_f":"Culture_medium",
	"meas_method":"plate_count",
	"condition":"NaCl(%):4, anaerobic",
	"temp":"19",
	"pH":"6.5",
	"aw":"0.977",
	"property":"",
	"tObs":"315.5",
	"logc":"0;3.03;70.5;3.55;95;3.62;118.5;3.98;142.5;4.43;167;4.86;240.5;7.19;265.5;7.09;290;7.14;315.5;7.14",
	"logcVar":"4.16",
	"spec_rate":"0.07037",
	"assumed":"aw",
	"comment":"",
	"in_on":"In: BHIB"
},
{
	"key":"H29_0C",
	"organism":"Sf",
	"specification":"Strain(s): 5348",
	"source":"Zaika_94",
	"details":"SfB01",
	"b_f":"Culture_medium",
	"meas_method":"plate_count",
	"condition":"NaCl(%):4, anaerobic",
	"temp":"19",
	"pH":"6.5",
	"aw":"0.977",
	"property":"",
	"tObs":"315.5",
	"logc":"0;3.03;70.5;2.98;95;2.61;118.5;2.9;142.5;3.46;167;4.06;240.5;6.38;265.5;5.92;290;7.16;315.5;7.18",
	"logcVar":"4.57",
	"spec_rate":"0.05432",
	"assumed":"aw",
	"comment":"",
	"in_on":"In: BHIB"
},
{
	"key":"H3_0A",
	"organism":"Sf",
	"specification":"Strain(s): 5348",
	"source":"Zaika_94",
	"details":"SfB01",
	"b_f":"Culture_medium",
	"meas_method":"plate_count",
	"condition":"NaCl(%):0.5, anaerobic",
	"temp":"19",
	"pH":"5.5",
	"aw":"0.997",
	"property":"",
	"tObs":"127.5",
	"logc":"0;3.02;24;3.33;48;4.66;120;8.46;124;8.28;127.5;8.48",
	"logcVar":"5.46",
	"spec_rate":"0.1069",
	"assumed":"aw",
	"comment":"",
	"in_on":"In: BHIB"
},
{
	"key":"H3_0B",
	"organism":"Sf",
	"specification":"Strain(s): 5348",
	"source":"Zaika_94",
	"details":"SfB01",
	"b_f":"Culture_medium",
	"meas_method":"plate_count",
	"condition":"NaCl(%):0.5, anaerobic",
	"temp":"19",
	"pH":"5.5",
	"aw":"0.997",
	"property":"",
	"tObs":"127.5",
	"logc":"0;3.02;24;3.53;48;5.13;120;8.63;124;8.4;127.5;8.79",
	"logcVar":"5.77",
	"spec_rate":"0.1081",
	"assumed":"aw",
	"comment":"",
	"in_on":"In: BHIB"
},
{
	"key":"H3_0C",
	"organism":"Sf",
	"specification":"Strain(s): 5348",
	"source":"Zaika_94",
	"details":"SfB01",
	"b_f":"Culture_medium",
	"meas_method":"plate_count",
	"condition":"NaCl(%):0.5, anaerobic",
	"temp":"19",
	"pH":"5.5",
	"aw":"0.997",
	"property":"",
	"tObs":"127.5",
	"logc":"0;3.02;24;3.54;48;5.15;120;8.56;124;8.39;127.5;8.51",
	"logcVar":"5.54",
	"spec_rate":"0.1843",
	"assumed":"aw",
	"comment":"",
	"in_on":"In: BHIB"
}
]
